{
  "PageID": 35608,
  "PageGuid": "1999c8e4-71da-4ae7-912b-30b0add6dea7",
  "Title": "topfact6 MyWork - MyWork FibuConnect - Übergabedatei erstellen",
  "Content": "Beginn Funktions-ID: 206 Modul-ID:62\r\nÜbergabedatei erstellen\r\nFertig kontierte Belege werden an die FiBu Übergabedatei übergeben. \r\n\r\n\r\n\r\n\r\nHinweis\r\nErfolgreich verarbeitet Belege werden im Archiv als verarbeitet gekennzeichnet. \r\nEnde Funktions-ID: 206 Modul-ID:62",
  "Url": "https://services.topfact.de/wiki/pages/view?g=1999c8e4-71da-4ae7-912b-30b0add6dea7"
}