{
  "PageID": 35699,
  "PageGuid": "36f58bb7-d513-4add-b990-9808d143fb34",
  "Title": "topfact6 MyWork - MyWork Dokumentenstruktur - Verlinkte Dokumente",
  "Content": "Beginn Funktions-ID: 258 Modul-ID:68\r\nVerlinkte Dokumente\r\nSucht verwandte Dokumente anhand eines Indexwertes des geöffneten Dokumentes. Das System gleicht die eingegeben Indexdaten des geöffneten Dokumentes mit den Indexdaten anderer Dokumente an und zeigt übereinstimmende Dokumente an.\r\n\r\n\r\n\r\nEnde Funktions-ID: 258 Modul-ID:68",
  "Url": "https://services.topfact.de/wiki/pages/view?g=36f58bb7-d513-4add-b990-9808d143fb34"
}